dagster_dbt/__init__.py
dagster_dbt/asset_defs.py
dagster_dbt/dbt_resource.py
dagster_dbt/errors.py
dagster_dbt/ops.py
dagster_dbt/types.py
dagster_dbt/utils.py
dagster_dbt/version.py
dagster_dbt/cli/__init__.py
dagster_dbt/cli/constants.py
dagster_dbt/cli/resources.py
dagster_dbt/cli/types.py
dagster_dbt/cli/utils.py
dagster_dbt/cloud/__init__.py
dagster_dbt/cloud/ops.py
dagster_dbt/cloud/resources.py
dagster_dbt/cloud/types.py
dagster_dbt/rpc/__init__.py
dagster_dbt/rpc/resources.py
dagster_dbt/rpc/types.py
dagster_dbt/rpc/utils.py
dagster_dbt-1.0.5.dist-info/LICENSE
dagster_dbt-1.0.5.dist-info/METADATA
dagster_dbt-1.0.5.dist-info/WHEEL
dagster_dbt-1.0.5.dist-info/top_level.txt
dagster_dbt-1.0.5.dist-info/RECORD
