Metadata-Version: 2.1
Name: dagster-dbt
Version: 1.0.5
Summary: A Dagster integration for dbt
Home-page: https://github.com/dagster-io/dagster/tree/master/python_modules/libraries/dagster-dbt
Author: Elementl
Author-email: hello@elementl.com
License: Apache-2.0
Platform: UNKNOWN
Classifier: Programming Language :: Python :: 3.7
Classifier: Programming Language :: Python :: 3.8
Classifier: Programming Language :: Python :: 3.9
Classifier: Programming Language :: Python :: 3.10
Classifier: License :: OSI Approved :: Apache Software License
Classifier: Operating System :: OS Independent
License-File: LICENSE
Requires-Dist: dagster (==1.0.5)
Requires-Dist: dagster-pandas (==1.0.5)
Requires-Dist: dbt-core
Requires-Dist: pandas
Requires-Dist: requests
Requires-Dist: attrs
Requires-Dist: agate
Provides-Extra: test
Requires-Dist: Jinja2 ; extra == 'test'
Requires-Dist: dbt-rpc ; extra == 'test'
Requires-Dist: dbt-postgres ; extra == 'test'
Requires-Dist: matplotlib ; extra == 'test'
